qcpalm/__init__.py
qcpalm/visualization.py
qcPALM-0.0.1.dist-info/LICENSE.md
qcPALM-0.0.1.dist-info/METADATA
qcPALM-0.0.1.dist-info/WHEEL
qcPALM-0.0.1.dist-info/top_level.txt
qcPALM-0.0.1.dist-info/RECORD
