Metadata-Version: 2.1
Name: qcPALM
Version: 0.0.1
Summary: Quantitative clustering of PALM data
Author-email: Shawn Yoshida <shawnryoshida@gmail.com>
Classifier: Programming Language :: Python :: 3
Classifier: License :: OSI Approved :: MIT License
Classifier: Operating System :: OS Independent
Requires-Python: >=3.7
License-File: LICENSE.md
